indieauth_helpers/__init__.py
indieauth_helpers/main.py
indieauth_helpers-1.0.1.dist-info/LICENSE.md
indieauth_helpers-1.0.1.dist-info/METADATA
indieauth_helpers-1.0.1.dist-info/WHEEL
indieauth_helpers-1.0.1.dist-info/top_level.txt
indieauth_helpers-1.0.1.dist-info/RECORD
