Metadata-Version: 2.1
Name: indieauth-helpers
Version: 1.0.1
Summary: IndieAuth authorization and callback helpers.
Home-page: https://github.com/capjamesg/python-indieauth-helpers
Author: capjamesg
Author-email: jamesg@jamesg.blog
License: UNKNOWN
Project-URL: Bug Tracker, https://github.com/capjamesg/python-indieauth-helpers/issues
Platform: UNKNOWN
Classifier: Programming Language :: Python :: 3
Classifier: License :: OSI Approved :: MIT License
Classifier: Operating System :: OS Independent
Requires-Python: >=3.6
License-File: LICENSE.md
